{
    "@context": "000_context.jsonld",
    "id": "amip-p4k",
    "type": "experiment",
    "min_number_yrs_per_sim": 44,
    "end_year": null,
    "description": "The same as the `amip` DECK experiment, except that SSTs are subject to a uniform warming of 4K. This warming should be applied to the ice-free ocean surface only. Sea ice and SSTs in grid boxes containing sea ice remain the same as in the `amip` DECK experiment.  Reference: [Webb et al., 2017](https://doi.org/10.5194/gmd-10-359-2017)",
    "experiment": "AMIP experiment with uniform 4K SST increase",
    "start_year": "1979-01-01",
    "additional_allowed_model_components": [
        "aer",
        "bgc",
        "chem"
    ],
    "activity": [
        "cfmip"
    ],
    "experiment_id": "amip-p4k"
}